dcid_server_sdk/__init__.py
dcid_server_sdk/client.py
dcid_server_sdk/types.py
dcid_server_sdk/config/__init__.py
dcid_server_sdk/config/environments.py
dcid_server_sdk/modules/__init__.py
dcid_server_sdk/modules/analytics/__init__.py
dcid_server_sdk/modules/analytics/analytics.py
dcid_server_sdk/modules/analytics/types.py
dcid_server_sdk/modules/auth/__init__.py
dcid_server_sdk/modules/auth/otp.py
dcid_server_sdk/modules/identity/__init__.py
dcid_server_sdk/modules/identity/encryption/__init__.py
dcid_server_sdk/modules/identity/encryption/key_manager.py
dcid_server_sdk/modules/identity/ipfs/__init__.py
dcid_server_sdk/modules/identity/ipfs/ipfs.py
dcid_server_sdk/modules/identity/issuer/__init__.py
dcid_server_sdk/modules/identity/issuer/issuer.py
dcid_server_sdk/modules/identity/verification/__init__.py
dcid_server_sdk/modules/identity/verification/verification.py
dcid_server_sdk/utils/__init__.py
dcid_server_sdk/utils/http.py
dcid_server_sdk/utils/logger.py
dcid_server_sdk-0.1.0.dist-info/licenses/LICENSE
dcid_server_sdk-0.1.0.dist-info/METADATA
dcid_server_sdk-0.1.0.dist-info/WHEEL
dcid_server_sdk-0.1.0.dist-info/top_level.txt
dcid_server_sdk-0.1.0.dist-info/RECORD
