Metadata-Version: 2.4
Name: dcid-server-sdk
Version: 0.1.0
Summary: Python SDK for DCID Server - Authentication and Identity operations
Author: DCID
License-Expression: ISC
Project-URL: Homepage, https://github.com/gettrustid/dcid-backend-sdk
Project-URL: Repository, https://github.com/gettrustid/dcid-backend-sdk
Project-URL: Issues, https://github.com/gettrustid/dcid-backend-sdk/issues
Classifier: Development Status :: 3 - Alpha
Classifier: Intended Audience :: Developers
Classifier: Programming Language :: Python :: 3
Classifier: Programming Language :: Python :: 3.8
Classifier: Programming Language :: Python :: 3.9
Classifier: Programming Language :: Python :: 3.10
Classifier: Programming Language :: Python :: 3.11
Classifier: Programming Language :: Python :: 3.12
Classifier: Operating System :: OS Independent
Requires-Python: >=3.8
License-File: LICENSE
Requires-Dist: requests>=2.28.0
Provides-Extra: server
Requires-Dist: fastapi>=0.104.0; extra == "server"
Requires-Dist: uvicorn[standard]>=0.24.0; extra == "server"
Requires-Dist: pydantic>=2.0.0; extra == "server"
Provides-Extra: dev
Requires-Dist: pytest>=7.0.0; extra == "dev"
Requires-Dist: pytest-cov>=4.0.0; extra == "dev"
Requires-Dist: black>=23.0.0; extra == "dev"
Requires-Dist: mypy>=1.0.0; extra == "dev"
Dynamic: license-file
